{"version":1,"resource":"file:///home/fais/punk.systems/code/esp32/punk.os/include/background.h","entries":[{"id":"648y.h","timestamp":1725473117310},{"id":"eMYq.h","timestamp":1725473138069},{"id":"DyAm.h","timestamp":1725473152035},{"id":"PD3k.h","timestamp":1725473258421},{"id":"Qtkq.h","timestamp":1725473277514},{"id":"y9AX.h","timestamp":1725473324235},{"id":"J6WM.h","timestamp":1725473383313},{"id":"vdWu.h","timestamp":1725473456643},{"id":"KUrv.h","timestamp":1725473485776},{"id":"bgIq.h","timestamp":1725475722561},{"id":"RNjW.h","timestamp":1725475760632},{"id":"UHc2.h","timestamp":1725475826139},{"id":"bttd.h","timestamp":1725475847118},{"id":"h5cb.h","timestamp":1725514342444},{"id":"6Zuj.h","timestamp":1725514363447},{"id":"1Gsn.h","timestamp":1725514378340},{"id":"Eo7m.h","timestamp":1725514415988},{"id":"vJOf.h","timestamp":1725514535447},{"id":"bAtT.h","timestamp":1725514555316}]}